cheesemonger/__init__.py
cheesemonger/reculture.py
cheesemonger/wheel_info.py
cheesemonger-0.1.dist-info/DESCRIPTION.rst
cheesemonger-0.1.dist-info/METADATA
cheesemonger-0.1.dist-info/RECORD
cheesemonger-0.1.dist-info/WHEEL
cheesemonger-0.1.dist-info/entry_points.txt
cheesemonger-0.1.dist-info/metadata.json
cheesemonger-0.1.dist-info/top_level.txt
