Metadata-Version: 2.0
Name: cheesemonger
Version: 0.1
Summary: A bunch of tools for manipulating wheels
Home-page: http://cheesemonger.rtfd.org
Author: James Tocknell
Author-email: aragilar@gmail.com
License: BSD
Keywords: wheel
Platform: UNKNOWN
Classifier: Development Status :: 3 - Alpha
Classifier: Intended Audience :: Developers
Classifier: Topic :: System :: Shells
Classifier: License :: OSI Approved :: BSD License
Classifier: Programming Language :: Python :: 2
Classifier: Programming Language :: Python :: 2.6
Classifier: Programming Language :: Python :: 2.7
Classifier: Programming Language :: Python :: 3
Classifier: Programming Language :: Python :: 3.1
Classifier: Programming Language :: Python :: 3.2
Classifier: Programming Language :: Python :: 3.3
Classifier: Programming Language :: Python :: 3.4
Requires-Dist: appdirs
Requires-Dist: distlib
Requires-Dist: logbook
Requires-Dist: venv-tools
Requires-Dist: virtualenv
